[{"title": "太朴有机会 红米2022新米红糙米饭红米杂粮五谷粗粮饭500gX4", "price": "79.00", "sales": "68人付款", "location": "贵州 贵阳", "shop_name": "太朴有机会旗舰店", "detail_url": "太朴有机会旗舰店"}, {"title": "2022新米东北大米延边粳米珍珠米软糯胚芽米寿司米真空越光米10斤", "price": "59.80", "sales": "300+人付款", "location": "吉林 延边朝鲜族", "shop_name": "野草冰", "detail_url": "野草冰"}, {"title": "十月稻田生态稻香米5kg 东北大米粳米香米10斤2022年新米", "price": "128.00", "sales": "3人付款", "location": "辽宁 沈阳", "shop_name": "十月稻田旗舰店", "detail_url": "十月稻田旗舰店"}, {"title": "状元州宜春珍硒大米10斤长粒香米江西宜春特产米含硒新米5kg包邮", "price": "63.00", "sales": "85人付款", "location": "江西 宜春", "shop_name": "宜春硒特产", "detail_url": "宜春硒特产"}, {"title": "台山珍香四星丝苗米20斤小农粘餐馆煲仔饭蒸饭大米10kg非泰国香米", "price": "108.00", "sales": "85人付款", "location": "广东 江门", "shop_name": "浪漫小宅", "detail_url": "浪漫小宅"}, {"title": "半天妖大米风光里五常大米不抬头臻品烤鱼专用米新米", "price": "94.00", "sales": "85人付款", "location": "山东 青岛", "shop_name": "津味坊", "detail_url": "津味坊"}, {"title": "2022年新米江苏大米一级软糯香甜粳米10kg煮粥米饭20斤促销珍珠米", "price": "53.50", "sales": "85人付款", "location": "江苏 南通", "shop_name": "南通富之康米业", "detail_url": "南通富之康米业"}, {"title": "2022新米梅河口大米秋田小町寿司米宝宝粥米包邮珍珠米小粒米圆粒", "price": "64.99", "sales": "85人付款", "location": "吉林 长春", "shop_name": "a0951116", "detail_url": "a0951116"}, {"title": "天王贡长粒香米5kg 东北大米10斤 黑龙江2022年新米包邮", "price": "39.80", "sales": "85人付款", "location": "黑龙江 哈尔滨", "shop_name": "tb852878619", "detail_url": "tb852878619"}, {"title": "东北大米2022年新米，长粒米，长粒香10斤", "price": "45.00", "sales": "85人付款", "location": "吉林 通化", "shop_name": "启慧核桃油", "detail_url": "启慧核桃油"}, {"title": "特五粱红官方有机稻花香2号五常大米15kg一等级东北2022新特30斤", "price": "599.00", "sales": "85人付款", "location": "上海", "shop_name": "五粱红旗舰店", "detail_url": "五粱红旗舰店"}, {"title": "贵朝米桂朝米潮糙籼米贵州凉糕凉虾米豆腐糯米糍粑专用大米5斤装", "price": "22.50", "sales": "89人付款", "location": "四川 成都", "shop_name": "蕾婷雅阁", "detail_url": "蕾婷雅阁"}, {"title": "2022年新大米一级江苏大米20斤软糯香甜清香米南粳9108珍珠米10kg", "price": "59.50", "sales": "85人付款", "location": "江苏 南通", "shop_name": "南通富之康米业", "detail_url": "南通富之康米业"}, {"title": "2022年新米新鲜大米真空长粒猫牙香米原生态农家米晚稻丝苗米炒饭", "price": "15.80", "sales": "89人付款", "location": "广西 贺州", "shop_name": "新农人村长好米", "detail_url": "新农人村长好米"}, {"title": "正宗东北五常大米2022新米gbt19266稻花香2号米牛粪肥嘎嘎香10kg", "price": "146.00", "sales": "84人付款", "location": "黑龙江 哈尔滨", "shop_name": "安静772014", "detail_url": "安静772014"}, {"title": "大米新米2022年新米柴火大院长粒香米5kg*4袋装东北大米黑龙江米", "price": "220.00", "sales": "84人付款", "location": "辽宁 沈阳", "shop_name": "柴火大院旗舰店", "detail_url": "柴火大院旗舰店"}, {"title": "延边大米鸭田小町珍珠米20斤包邮东北农家自产圆粒小粒香米延吉米", "price": "85.50", "sales": "84人付款", "location": "吉林 延边朝鲜族", "shop_name": "延边特产8575", "detail_url": "延边特产8575"}, {"title": "22年东北新大米10斤 农家圆粒米 香米珍珠香米吉林粳米秋田小町", "price": "40.80", "sales": "84人付款", "location": "吉林", "shop_name": "皓月当曌", "detail_url": "皓月当曌"}, {"title": "金龙鱼江南丝苗米5kg南方大米优质籼米10斤低氧保鲜包装 特惠包邮", "price": "49.90", "sales": "84人付款", "location": "", "shop_name": "安徽原产地商品官方旗舰店", "detail_url": "安徽原产地商品官方旗舰店"}, {"title": "19266五常稻花香2号大米100斤东北长粒香新米 2022新磨真空袋50斤", "price": "33.98", "sales": "84人付款", "location": "黑龙江 哈尔滨", "shop_name": "客马良仓企业店", "detail_url": "客马良仓企业店"}, {"title": "雪乡农家东北黑土地响水石板大米5kg 大米 新米 牡丹江石板大米", "price": "108.00", "sales": "84人付款", "location": "江苏 南京", "shop_name": "本来生活旗舰店", "detail_url": "本来生活旗舰店"}, {"title": "猫牙米大米5 10kg长粒香大米超长丝苗米2022年新米香米10斤20斤", "price": "43.00", "sales": "84人付款", "location": "广西 南宁", "shop_name": "绿果沟旗舰店", "detail_url": "绿果沟旗舰店"}, {"title": "Y燕迎春东北长粒香大米10斤真空装吉林当季新米5kg农家稻香粳米", "price": "37.90", "sales": "84人付款", "location": "吉林", "shop_name": "燕迎春旗舰店", "detail_url": "燕迎春旗舰店"}, {"title": "五常大米10kg新米19266正宗长粒米饭煮粥占你心东北稻花香2号20斤", "price": "136.00", "sales": "84人付款", "location": "黑龙江 大庆", "shop_name": "占你心粮油旗舰店", "detail_url": "占你心粮油旗舰店"}, {"title": "湖南长粒香大米2.5kg小包装新米2022年油粘丝苗米煲仔饭专用米5斤", "price": "23.00", "sales": "88人付款", "location": "湖南 岳阳", "shop_name": "尚品保证", "detail_url": "尚品保证"}, {"title": "福临门大米水晶米5kg香软可口晶莹剔透粳米宜煮粥香米10斤装", "price": "29.90", "sales": "1000+人付款", "location": "上海", "shop_name": "天猫超市", "detail_url": "天猫超市"}, {"title": "十月香大米东北大米长粒香米10kg2022年新米真空锁鲜软香粳米20斤", "price": "79.90", "sales": "1000+人付款", "location": "上海", "shop_name": "天猫超市", "detail_url": "天猫超市"}, {"title": "增荔丝苗米增城特产5kg南方籼米煲仔饭专用米家庭装10斤大米", "price": "39.90", "sales": "1000+人付款", "location": "上海", "shop_name": "天猫超市", "detail_url": "天猫超市"}, {"title": "喵满分自有品牌五常大米10kg20斤龙凤山五优稻4号23新米兔年礼盒", "price": "199.90", "sales": "1000+人付款", "location": "上海", "shop_name": "天猫超市", "detail_url": "天猫超市"}, {"title": "荆楚大地大米臻选寒地珍珠米10kg东北大米圆粒米一级粳米20斤", "price": "69.90", "sales": "1000+人付款", "location": "上海", "shop_name": "天猫超市", "detail_url": "天猫超市"}, {"title": "掌中禾东北大米粒粒香2.5kg东北核心产区粳米香米珍珠米5斤A", "price": "27.80", "sales": "88人付款", "location": "黑龙江 哈尔滨", "shop_name": "掌中禾旗舰店", "detail_url": "掌中禾旗舰店"}, {"title": "【尝鲜装】 十月稻田东北长粒香大米2.5kg 黑龙江粳米2022年新米", "price": "49.90", "sales": "83人付款", "location": "辽宁 沈阳", "shop_name": "十月稻田旗舰店", "detail_url": "十月稻田旗舰店"}, {"title": "米饭要讲究钱塘老娘舅大米10kg现碾江南鲜米宝宝米软糯香20斤包邮", "price": "58.90", "sales": "83人付款", "location": "江苏 泰州", "shop_name": "tb8692403055", "detail_url": "tb8692403055"}, {"title": "小毕朗遮放软米10斤 云南德宏特产大米新米软香稻米粳米南方籼米", "price": "39.80", "sales": "83人付款", "location": "云南 昆明", "shop_name": "速果水果专营店", "detail_url": "速果水果专营店"}, {"title": "不好吃包退正宗南方大米长粒香煲仔饭丝苗米10kg20斤一年一季籼米", "price": "59.40", "sales": "83人付款", "location": "江苏 淮安", "shop_name": "创亿眼镜批发商城", "detail_url": "创亿眼镜批发商城"}, {"title": "黑龙江东北大米 寒香玉营养强化米 长粒香大米5kg10斤装 全国包邮", "price": "38.80", "sales": "83人付款", "location": "黑龙江 哈尔滨", "shop_name": "hxydm2018", "detail_url": "hxydm2018"}, {"title": "2023年新米猫牙大米长条米煲仔饭丝苗米油粘米籼米长粒香米农家米", "price": "12.80", "sales": "87人付款", "location": "广西 贺州", "shop_name": "新农人村长好米", "detail_url": "新农人村长好米"}, {"title": "迎甜10斤长粒香大米5kg5斤稻花香大米正宗农家自产东北大米新米", "price": "22.80", "sales": "83人付款", "location": "黑龙江 哈尔滨", "shop_name": "迎甜旗舰店", "detail_url": "迎甜旗舰店"}, {"title": "宝宝胚芽米婴幼儿大米一岁无农药粳米原生态东北珍珠米胚芽吃的粥", "price": "56.00", "sales": "83人付款", "location": "辽宁 铁岭", "shop_name": "tianzun00syy", "detail_url": "tianzun00syy"}, {"title": "2022年超长粒猫牙甄选大米5kg五常新米软糯丝苗10kg真空东方香米", "price": "38.00", "sales": "83人付款", "location": "广西 南宁", "shop_name": "螺大厨美食", "detail_url": "螺大厨美食"}, {"title": "五常稻花香米20斤装【新米】20年新大米正宗东北长粒米稻香米10斤", "price": "15.93", "sales": "83人付款", "location": "山西 晋城", "shop_name": "tb070228810", "detail_url": "tb070228810"}, {"title": "农家大米无公害大米5斤包邮【新粉限拍一单】", "price": "22.00", "sales": "87人付款", "location": "江西 上饶", "shop_name": "泽强电器", "detail_url": "泽强电器"}, {"title": "井冈山红米新米糙米五谷杂粮红米饭玄米红粳米红大米粗粮特产5斤", "price": "13.20", "sales": "87人付款", "location": "江西 吉安", "shop_name": "designer198", "detail_url": "designer198"}, {"title": "【专享】葵花阳光五常大米官方旗舰店稻花香2号东北大米5kg", "price": "72.00", "sales": "82人付款", "location": "黑龙江 哈尔滨", "shop_name": "葵花阳光旗舰店", "detail_url": "葵花阳光旗舰店"}]